<?xml version="1.0" encoding="utf-8" ?>
<dwsync>
<file name="jqxcore.js" server="C:/AppServ/www/appl/VidrieriaWeb/" local="130676281360000000" remote="130676281360000000" />
<file name="jqxbuttons.js" server="C:/AppServ/www/appl/VidrieriaWeb/" local="130676281360000000" remote="130676281360000000" />
<file name="jqxscrollbar.js" server="C:/AppServ/www/appl/VidrieriaWeb/" local="130676281360000000" remote="130676281360000000" />
<file name="jqxmenu.js" server="C:/AppServ/www/appl/VidrieriaWeb/" local="130681468980000000" remote="130681468980000000" />
<file name="jqxdatatable.js" server="C:/AppServ/www/appl/VidrieriaWeb/" local="130778660480829093" remote="130778660480000000" />
<file name="jqxgrid.js" server="C:/AppServ/www/appl/VidrieriaWeb/" local="130778667139879969" remote="130778667130000000" />
<file name="jqxgrid.selection.js" server="C:/AppServ/www/appl/VidrieriaWeb/" local="130676281340000000" remote="130676281340000000" />
<file name="jqxgrid.filter.js" server="C:/AppServ/www/appl/VidrieriaWeb/" local="130676281340000000" remote="130676281340000000" />
<file name="jqxgrid.sort.js" server="C:/AppServ/www/appl/VidrieriaWeb/" local="130676281340000000" remote="130676281340000000" />
<file name="jqxgrid.edit.js" server="C:/AppServ/www/appl/VidrieriaWeb/" local="130676281340000000" remote="130676281340000000" />
<file name="jqxgrid.pager.js" server="C:/AppServ/www/appl/VidrieriaWeb/" local="130676281340000000" remote="130676281340000000" />
<file name="jqxgrid.aggregates.js" server="C:/AppServ/www/appl/VidrieriaWeb/" local="130676281340000000" remote="130676281340000000" />
<file name="jqxknockout.js" server="C:/AppServ/www/appl/VidrieriaWeb/" local="130676281360000000" remote="130676281360000000" />
<file name="jqxcheckbox.js" server="C:/AppServ/www/appl/VidrieriaWeb/" local="130676281360000000" remote="130676281360000000" />
<file name="jqxdata.js" server="C:/AppServ/www/appl/VidrieriaWeb/" local="130676281340000000" remote="130676281340000000" />
<file name="jqxlistbox.js" server="C:/AppServ/www/appl/VidrieriaWeb/" local="130676281360000000" remote="130676281360000000" />
<file name="jqxcombobox.js" server="C:/AppServ/www/appl/VidrieriaWeb/" local="130676281360000000" remote="130676281360000000" />
<file name="jqxdropdownlist.js" server="C:/AppServ/www/appl/VidrieriaWeb/" local="130676281360000000" remote="130676281360000000" />
<file name="jqxwindow.js" server="C:/AppServ/www/appl/VidrieriaWeb/" local="130676281340000000" remote="130676281340000000" />
<file name="jqxinput.js" server="C:/AppServ/www/appl/VidrieriaWeb/" local="130676281360000000" remote="130676281360000000" />
<file name="jqxnumberinput.js" server="C:/AppServ/www/appl/VidrieriaWeb/" local="130676281360000000" remote="130676281360000000" />
<file name="jqxmaskedinput.js" server="C:/AppServ/www/appl/VidrieriaWeb/" local="130676281360000000" remote="130676281360000000" />
<file name="jqxdatetimeinput.js" server="C:/AppServ/www/appl/VidrieriaWeb/" local="130676281360000000" remote="130676281360000000" />
<file name="jqxcalendar.js" server="C:/AppServ/www/appl/VidrieriaWeb/" local="130676281360000000" remote="130676281360000000" />
<file name="jqxdata.export.js" server="C:/AppServ/www/appl/VidrieriaWeb/" local="130676281360000000" remote="130676281360000000" />
<file name="jqxgrid.export.js" server="C:/AppServ/www/appl/VidrieriaWeb/" local="130676281360000000" remote="130676281360000000" />
<file name="jqxtooltip.js" server="C:/AppServ/www/appl/VidrieriaWeb/" local="130676281360000000" remote="130676281360000000" />
<file name="jqxslider.js" server="C:/AppServ/www/appl/VidrieriaWeb/" local="130676281340000000" remote="130676281340000000" />
</dwsync>